__init__.py
swapsys.py
swapsys-1.0.1.dist-info/LICENCE
swapsys-1.0.1.dist-info/METADATA
swapsys-1.0.1.dist-info/WHEEL
swapsys-1.0.1.dist-info/entry_points.txt
swapsys-1.0.1.dist-info/top_level.txt
swapsys-1.0.1.dist-info/RECORD
